MixacLib/__init__.py
MixacLib/cons.py
MixacLib_tumuidle-1.0.0.dist-info/LICENSE
MixacLib_tumuidle-1.0.0.dist-info/METADATA
MixacLib_tumuidle-1.0.0.dist-info/WHEEL
MixacLib_tumuidle-1.0.0.dist-info/top_level.txt
MixacLib_tumuidle-1.0.0.dist-info/RECORD
