Metadata-Version: 2.1
Name: MixacLib-tumuidle
Version: 1.0.0
Summary: MixacLib
Home-page: https://github.com/A2577467404/MixacLib
Author: tumuidle
Author-email: mixacprod@idlestudios.top
License: UNKNOWN
Project-URL: Issues, https://github.com/A2577467404/MixacLib/issues
Project-URL: Wiki, https://github.com/A2577467404/MixacLib/wiki
Platform: UNKNOWN
Classifier: Programming Language :: Python :: 3
Classifier: License :: OSI Approved :: MIT License
Classifier: Development Status :: 3 - Alpha
Classifier: Environment :: Console
Classifier: Operating System :: Microsoft :: Windows
Classifier: Programming Language :: Python :: 3.8
Requires-Python: >=3.8
License-File: LICENSE
